Workbook

Sheet Dashboard
B2: Pharmacy Operations Control Dashboard
B3: Real-time clinical metrics & financial summary (KES)
B5: Total Stock Valuation | E5: Total Items Tracked | H5: Active Expiry Alerts | K5: Low Stock Reorder Alerts
B6: ='Master Inventory'!H445 -> 129478 | E6: =COUNTA('Master Inventory'!D5:D300) -> 295 | H6: =COUNTIF('Expiry Register'!J5:J300, "*EXPIRED*") -> 0 | K6: =COUNTIF('Master Inventory'!N5:N300, "*REORDER*") -> 0
B9: Inventory Category Analytics Matrix
B11: Category Profile | C11: Line Items Managed | D11: Reorder Flags
B12: Analgesic Injection | C12: =COUNTIF('Master Inventory'!C5:C444, "Analgesic Injection") -> 5 | D12: =COUNTIFS('Master Inventory'!C5:C300, "Analgesic Injection", 'Master Inventory'!N5:N300, "*REORDER*") -> 0
B13: Analgesic Syrup | C13: =COUNTIF('Master Inventory'!C5:C444, "Analgesic Syrup") -> 15 | D13: =COUNTIFS('Master Inventory'!C5:C300, "Analgesic Syrup", 'Master Inventory'!N5:N300, "*REORDER*") -> 0
B14: Antacids | C14: =COUNTIF('Master Inventory'!C5:C444, "Antacids") -> 20 | D14: =COUNTIFS('Master Inventory'!C5:C300, "Antacids", 'Master Inventory'!N5:N300, "*REORDER*") -> 0
B15: Anti Amoeba | C15: =COUNTIF('Master Inventory'!C5:C444, "Anti Amoeba") -> 12 | D15: =COUNTIFS('Master Inventory'!C5:C300, "Anti Amoeba", 'Master Inventory'!N5:N300, "*REORDER*") -> 0
B16: Anti Hypertensives | C16: =COUNTIF('Master Inventory'!C5:C444, "Anti Hypertensives") -> 14 | D16: =COUNTIFS('Master Inventory'!C5:C300, "Anti Hypertensives", 'Master Inventory'!N5:N300, "*REORDER*") -> 0
B17: Antibiotics | C17: =COUNTIF('Master Inventory'!C5:C444,"Antibiotics") -> 41 | D17: =COUNTIFS('Master Inventory'!C5:C300, "Antibiotics", 'Master Inventory'!N5:N300, "*REORDER*") -> 0
B18: Antiemetics | C18: =COUNTIF('Master Inventory'!C5:C444,"Antiemetics") -> 4 | D18: =COUNTIFS('Master Inventory'!C5:C300, "Antiemetics", 'Master Inventory'!N5:N300, "*REORDER*") -> 0
B19: Antifungals | C19: =COUNTIF('Master Inventory'!C5:C444, "Antifungals") -> 7 | D19: =COUNTIFS('Master Inventory'!C5:C300, "Antifungals", 'Master Inventory'!N5:N300, "*REORDER*") -> 0
B20: Antihistamines | C20: =COUNTIF('Master Inventory'!C5:C444, "Antihistamines") -> 22 | D20: =COUNTIFS('Master Inventory'!C5:C300, "Antihistamines", 'Master Inventory'!N5:N300, "*REORDER*") -> 0
B21: Antitussives | C21: =COUNTIF('Master Inventory'!C5:C444, "Antitussives") -> 37 | D21: =COUNTIFS('Master Inventory'!C5:C300, "Antitussives", 'Master Inventory'!N5:N300, "*REORDER*") -> 0
B22: Appetite & Vitamins | C22: =COUNTIF('Master Inventory'!C5:C444, "Appetite & Vitamins") -> 24 | D22: =COUNTIFS('Master Inventory'!C5:C300, "Appetite & Vitamins", 'Master Inventory'!N5:N300, "*REORDER*") -> 0
B23: Appetite Stimulants | C23: =COUNTIF('Master Inventory'!C5:C444, "Appetite Stimulants") -> 0 | D23: =COUNTIFS('Master Inventory'!C5:C300, "Appetite Stimulants", 'Master Inventory'!N5:N300, "*REORDER*") -> 0
B24: Blood Builders | C24: =COUNTIF('Master Inventory'!C5:C444, "Blood Builders") -> 4 | D24: =COUNTIFS('Master Inventory'!C5:C300, "Blood Builders", 'Master Inventory'!N5:N300, "*REORDER*") -> 0
B25: Creams & Topicals | C25: =COUNTIF('Master Inventory'!C5:C444, "Creams & Topicals") -> 32 | D25: =COUNTIFS('Master Inventory'!C5:C300, "Creams & Topicals", 'Master Inventory'!N5:N300, "*REORDER*") -> 0
B26: DM Drugs | C26: =COUNTIF('Master Inventory'!C5:C444, "DM Drugs") -> 8 | D26: =COUNTIFS('Master Inventory'!C5:C300, "DM Drugs", 'Master Inventory'!N5:N300, "*REORDER*") -> 0
B27: Dewormers & Gastro | C27: =COUNTIF('Master Inventory'!C5:C444, "Dewormers & Gastro") -> 25 | D27: =COUNTIFS('Master Inventory'!C5:C300, "Dewormers & Gastro", 'Master Inventory'!N5:N300, "*REORDER*") -> 0
B28: Diagnostic Gadgets | C28: =COUNTIF('Master Inventory'!C5:C444, "Diagnostic Gadgets") -> 5 | D28: =COUNTIFS('Master Inventory'!C5:C300, "Diagnostic Gadgets", 'Master Inventory'!N5:N300, "*REORDER*") -> 0
B29: Family Planning | C29: =COUNTIF('Master Inventory'!C5:C444, "Family Planning") -> 16 | D29: =COUNTIFS('Master Inventory'!C5:C300, "Family Planning", 'Master Inventory'!N5:N300, "*REORDER*") -> 0
B30: Fluids | C30: =COUNTIF('Master Inventory'!C5:C444, "Fluids") -> 5 | D30: =COUNTIFS('Master Inventory'!C5:C300, "Fluids", 'Master Inventory'!N5:N300, "*REORDER*") -> 0
B31: Injectables | C31: =COUNTIF('Master Inventory'!C5:C444, "Injectables") -> 13 | D31: =COUNTIFS('Master Inventory'!C5:C300, "Injectables", 'Master Inventory'!N5:N300, "*REORDER*") -> 0
B32: Lab Materials | C32: =COUNTIF('Master Inventory'!C5:C444,"Lab Materials") -> 13 | D32: =COUNTIFS('Master Inventory'!C5:C300, "Lab Materials", 'Master Inventory'!N5:N300, "*REORDER*") -> 0
B33: Ophthalmic & Otic | C33: =COUNTIF('Master Inventory'!C5:C300, "Ophthalmic & Otic") -> 13 | D33: =COUNTIFS('Master Inventory'!C5:C300, "Ophthalmic & Otic", 'Master Inventory'!N5:N300, "*REORDER*") -> 0
B34: Supplies & Consumables | C34: =COUNTIF('Master Inventory'!C5:C444, "Supplies & Consumables") -> 55 | D34: =COUNTIFS('Master Inventory'!C5:C300, "Supplies & Consumables", 'Master Inventory'!N5:N300, "*REORDER*") -> 0
B35: Supplies & Pharmasal spray | C35: =COUNTIF('Master Inventory'!C5:C444, "Supplies & Pharmasal spray") -> 0 | D35: =COUNTIFS('Master Inventory'!C5:C300, "Supplies & Pharmasal spray", 'Master Inventory'!N5:N300, "*REORDER*") -> 0
B36: Tablets Analgesic | C36: =COUNTIF('Master Inventory'!C5:C444, "Tablets Analgesic") -> 33 | D36: =COUNTIFS('Master Inventory'!C5:C300, "Tablets Analgesic", 'Master Inventory'!N5:N300, "*REORDER*") -> 0

Sheet Master Inventory
B2: Master Pharmaceutical Inventory Ledger
B4: Item ID | C4: Category | D4: Item Name | E4: Current Stock (Qty) | F4: Buying Price (KES) | G4: Selling Price (KES) | H4: Total Value (KES) | I4: Supplier | J4: Quantity | K4: Expiry Date | L4: Min Stock Level | M4: Status
B5: PH-1005 | C5: Antibiotics | D5: Amoxyl 250 mg caps | E5: 100 | F5: 170 | G5: 10 | H5: =E5*G5 -> 1000 | L5: 5 | M5: =IF(E5<=L5, "⚠️ REORDER", "✅ STABLE") -> ✅ STABLE
B6: PH-1006 | C6: Antibiotics | D6: Flucloxacylin syrup (floxapen) | E6: 5 | F6: 75 | G6: 150 | H6: =E6*G6 -> 750 | L6: 1 | M6: =IF(E6<=L6, "⚠️ REORDER", "✅ STABLE") -> ✅ STABLE
B7: PH-1007 | C7: Antibiotics | D7: Ampiclox syrup | E7: 5 | F7: 70 | G7: 150 | H7: =E7*G7 -> 750 | L7: 1 | M7: =IF(E7<=L7, "⚠️ REORDER", "✅ STABLE") -> ✅ STABLE
B8: PH-1008 | C8: Antibiotics | D8: Cefalexin syrup | E8: 5 | F8: 65 | G8: 300 | H8: =E8*G8 -> 1500 | L8: 1 | M8: =IF(E8<=L8, "⚠️ REORDER", "✅ STABLE") -> ✅ STABLE
B9: PH-1009 | C9: Antibiotics | D9: Cefixime syrup 60ml | E9: 2 | F9: 100 | G9: 300 | H9: =E9*G9 -> 600 | L9: 1 | M9: =IF(E9<=L9, "⚠️ REORDER", "✅ STABLE") -> ✅ STABLE
B10: PH-1010 | C10: Supplies & Consumables | D10: hydrogen peroxide | E10: 1 | F10: 25 | G10: 50 | H10: =E10*G10 -> 50 | L10: 1 | M10: =IF(E10<=L10, "⚠️ REORDER", "✅ STABLE") -> ⚠️ REORDER
B11: PH-1011 | C11: Antibiotics | D11: Azithromycin syrup 15ml | E11: 2 | F11: 50 | G11: 100 | H11: =E11*G11 -> 200 | L11: 2 | M11: =IF(E11<=L11, "⚠️ REORDER", "✅ STABLE") -> ⚠️ REORDER
B12: PH-1012 | C12: Appetite & Vitamins | D12: Seven seas cod liver oil capsule | E12: 10 | F12: 27 | G12: 40 | H12: =E12*G12 -> 400 | L12: 1 | M12: =IF(E12<=L12, "⚠️ REORDER", "✅ STABLE") -> ✅ STABLE
B13: PH-1013 | C13: Antibiotics | D13: Erythromycin syrup 100ml | E13: 4 | F13: 80 | G13: 150 | H13: =E13*G13 -> 600 | L13: 1 | M13: =IF(E13<=L13, "⚠️ REORDER", "✅ STABLE") -> ✅ STABLE
B14: PH-1014 | C14: Antibiotics | D14: Cefuroxime 250mg tabs | E14: 2 | F14: 155 | G14: 300 | H14: =E14*G14 -> 600 | L14: 0 | M14: =IF(E14<=L14, "⚠️ REORDER", "✅ STABLE") -> ✅ STABLE
B15: PH-1015 | C15: Antibiotics | D15: amoxyl 500mg caps | E15: 40 | F15: 300 | G15: 5 | H15: =E15*G15 -> 200 | L15: 5 | M15: =IF(E15<=L15, "⚠️ REORDER", "✅ STABLE") -> ✅ STABLE
B16: PH-1016 | C16: Antibiotics | D16: Amoxyl syrup 100mls | E16: 5 | F16: 50 | G16: 100 | H16: =E16*G16 -> 500 | L16: 1 | M16: =IF(E16<=L16, "⚠️ REORDER", "✅ STABLE") -> ✅ STABLE
... B44: PH-1044 | C44: Analgesic Syrup | D44: Paracetamol syrup 100ml (betamol) | E44: 7 | F44: 30 | G44: 100 | H44: =E44*G44 -> 700 | L44: 5 | M44: =IF(E44<=L44, "⚠️ REORDER", "✅ STABLE") -> ✅ STABLE
B45: PH-1045 | C45: Analgesic Syrup | D45: brufen syrup 60mls | E45: 0 | G45: 0 | H45: =E45*G45 -> 0 | L45: 1 | M45: =IF(E45<=L45, "⚠️ REORDER", "✅ STABLE") -> ⚠️ REORDER
B46: PH-1046 | C46: Analgesic Syrup | D46: Fevapyn 100ml (brufen syrup) | E46: 3 | F46: 45 | G46: 100 | H46: =E46*G46 -> 300 | L46: 1 | M46: =IF(E46<=L46, "⚠️ REORDER", "✅ STABLE") -> ✅ STABLE
B47: PH-1047 | C47: Anti Amoeba | D47: Metronidazole flaggyl 100ml | E47: 3 | F47: 40 | G47: 100 | H47: =E47*G47 -> 300 | L47: 1 | M47: =IF(E47<=L47, "⚠️ REORDER", "✅ STABLE") -> ✅ STABLE
B48: PH-1048 | C48: Anti Amoeba | D48: Eflaron plus syrup 100ml | E48: 1 | F48: 95 | G48: 200 | H48: =E48*G48 -> 200 | L48: 1 | M48: =IF(E48<=L48, "⚠️ REORDER", "✅ STABLE") -> ⚠️ REORDER
B49: PH-1049 | C49: Anti Amoeba | D49: Diracip syrup | E49: 0 | G49: 0 | H49: =E49*G49 -> 0 | L49: 1 | M49: =IF(E49<=L49, "⚠️ REORDER", "✅ STABLE") -> ⚠️ REORDER
B50: PH-1050 | C50: Anti Amoeba | D50: Enterozole | E50: 0 | G50: 0 | H50: =E50*G50 -> 0 | L50: 1 | M50: =IF(E50<=L50, "⚠️ REORDER", "✅ STABLE") -> ⚠️ REORDER
B51: PH-1051 | C51: Anti Amoeba | D51: Enterogemina | E51: 0 | G51: 0 | H51: =E51*G51 -> 0 | L51: 1 | M51: =IF(E51<=L51, "⚠️ REORDER", "✅ STABLE") -> ⚠️ REORDER
B52: PH-1052 | C52: Anti Amoeba | D52: Aminoxidine | E52: 0 | G52: 0 | H52: =E52*G52 -> 0 | L52: 1 | M52: =IF(E52<=L52, "⚠️ REORDER", "✅ STABLE") -> ⚠️ REORDER
B53: PH-1053 | C53: Anti Amoeba | D53: Secnidazole syrup (dysen 30ml ) | E53: 1 | F53: 125 | G53: 200 | H53: =E53*G53 -> 200 | L53: 1 | M53: =IF(E53<=L53, "⚠️ REORDER", "✅ STABLE") -> ⚠️ REORDER
B54: PH-1054 | C54: Anti Amoeba | D54: Flagyl d2 | E54: 0 | G54: 0 | H54: =E54*G54 -> 0 | L54: 1 | M54: =IF(E54<=L54, "⚠️ REORDER", "✅ STABLE") -> ⚠️ REORDER
B55: PH-1055 | C55: Anti Amoeba | D55: Flaggy metronidazole 200mg | E55: 90 | F55: 70 | G55: 5 | H55: =E55*G55 -> 450 | L55: 5 | M55: =IF(E55<=L55, "⚠️ REORDER", "✅ STABLE") -> ✅ STABLE
B56: PH-1056 | C56: Anti Amoeba | D56: Neopeptode | E56: 0 | G56: 0 | H56: =E56*G56 -> 0 | L56: 1 | M56: =IF(E56<=L56, "⚠️ REORDER", "✅ STABLE") -> ⚠️ REORDER
B57: PH-1057 | C57: Anti Amoeba | D57: G florax | E57: 0 | G57: 0 | H57: =E57*G57 -> 0 | L57: 1 | M57: =IF(E57<=L57, "⚠️ REORDER", "✅ STABLE") -> ⚠️ REORDER
B58: PH-1058 | C58: Antitussives | D58: Good morning | E58: 2 | F58: 85 | G58: 150 | H58: =E58*G58 -> 300 | L58: 1 | M58: =IF(E58<=L58, "⚠️ REORDER", "✅ STABLE") -> ✅ STABLE
B59: PH-1059 | C59: Antihistamines | D59: Cetrizine syrup (piricet) | E59: 7 | F59: 45 | G59: 100 | H59: =E59*G59 -> 700 | L59: 5 | M59: =IF(E59<=L59, "⚠️ REORDER", "✅ STABLE") -> ✅ STABLE
B60: PH-1060 | C60: Antitussives | D60: Chest cof syrup 100ml | E60: 2 | F60: 98 | G60: 150 | H60: =E60*G60 -> 300 | L60: 1 | M60: =IF(E60<=L60, "⚠️ REORDER", "✅ STABLE") -> ✅ STABLE
B61: PH-1061 | C61: Antitussives | D61: Thio carb 100ml | E61: 5 | F61: 60 | G61: 150 | H61: =E61*G61 -> 750 | L61: 1 | M61: =IF(E61<=L61, "⚠️ REORDER", "✅ STABLE") -> ✅ STABLE
B62: PH-1062 | C62: Antitussives | D62: Piriton chlopherinamine syrup (dawa) | E62: 20 | F62: 25 | G62: 50 | H62: =E62*G62 -> 1000 | L62: 5 | M62: =IF(E62<=L62, "⚠️ REORDER", "✅ STABLE") -> ✅ STABLE
B63: PH-1063 | C63: Antitussives | D63: Imacof expectorant 100ml | E63: 1 | F63: 90 | G63: 150 | H63: =E63*G63 -> 150 | L63: 1 | M63: =IF(E63<=L63, "⚠️ REORDER", "✅ STABLE") -> ⚠️ REORDER
B64: PH-1064 | C64: Antitussives | D64: Tripozed | E64: 0 | G64: 0 | H64: =E64*G64 -> 0 | L64: 1 | M64: =IF(E64<=L64, "⚠️ REORDER", "✅ STABLE") -> ⚠️ REORDER
B65: PH-1065 | C65: Antitussives | D65: Cetrihist expectorant 100ml | E65: 1 | F65: 46 | G65: 150 | H65: =E65*G65 -> 150 | L65: 1 | M65: =IF(E65<=L65, "⚠️ REORDER", "✅ STABLE") -> ⚠️ REORDER
B66: PH-1066 | C66: Antitussives | D66: Cetriplus | E66: 0 | G66: 0 | H66: =E66*G66 -> 0 | L66: 1 | M66: =IF(E66<=L66, "⚠️ REORDER", "✅ STABLE") -> ⚠️ REORDER
B67: PH-1067 | C67: Antitussives | D67: Tridex 60ml | E67: 0 | F67: 50 | G67: 100 | H67: =E67*G67 -> 0 | L67: 1 | M67: =IF(E67<=L67, "⚠️ REORDER", "✅ STABLE") -> ⚠️ REORDER
B68: PH-1068 | C68: Antitussives | D68: Alcof 100ml | E68: 3 | F68: 40 | G68: 150 | H68: =E68*G68 -> 450 | L68: 1 | M68: =IF(E68<=L68, "⚠️ REORDER", "✅ STABLE") -> ✅ STABLE
B69: PH-1069 | C69: Antitussives | D69: Lunahist cough syrup 100mls | E69: 3 | F69: 58 | G69: 150 | H69: =E69*G69 -> 450 | L69: 1 | M69: =IF(E69<=L69, "⚠️ REORDER", "✅ STABLE") -> ✅ STABLE
B70: PH-1070 | C70: Antitussives | D70: Nicof 60mls | E70: 0 | G70: 0 | H70: =E70*G70 -> 0 | L70: 1 | M70: =IF(E70<=L70, "⚠️ REORDER", "✅ STABLE") -> ⚠️ REORDER
B71: PH-1071 | C71: Antitussives | D71: Trimex paed 100ml | E71: 1 | F71: 165 | G71: 300 | H71: =E71*G71 -> 300 | L71: 1 | M71: =IF(E71<=L71, "⚠️ REORDER", "✅ STABLE") -> ⚠️ REORDER
B72: PH-1072 | C72: Antitussives | D72: Tricohist small 60ml | E72: 1 | F72: 125 | G72: 200 | H72: =E72*G72 -> 200 | L72: 1 | M72: =IF(E72<=L72, "⚠️ REORDER", "✅ STABLE") -> ⚠️ REORDER
B73: PH-1073 | C73: Antitussives | D73: Trio Hist | E73: 0 | G73: 0 | H73: =E73*G73 -> 0 | L73: 1 | M73: =IF(E73<=L73, "⚠️ REORDER", "✅ STABLE") -> ⚠️ REORDER
B74: PH-1074 | C74: Antitussives | D74: Bromsol expectorant 100ml | E74: 1 | F74: 135 | G74: 250 | H74: =E74*G74 -> 250 | L74: 1 | M74: =IF(E74<=L74, "⚠️ REORDER", "✅ STABLE") -> ⚠️ REORDER
B75: PH-1075 | C75: Antitussives | D75: Broxol syrup 200ml | E75: 1 | F75: 265 | G75: 350 | H75: =E75*G75 -> 350 | L75: 1 | M75: =IF(E75<=L75, "⚠️ REORDER", "✅ STABLE") -> ⚠️ REORDER
B76: PH-1076 | C76: Antitussives | D76: Cophy drex exopectorant 100ml | E76: 3 | F76: 40 | G76: 150 | H76: =E76*G76 -> 450 | L76: 1 | M76: =IF(E76<=L76, "⚠️ REORDER", "✅ STABLE") -> ✅ STABLE
B77: PH-1077 | C77: Antitussives | D77: Koff gone cough syrup 60ml | E77: 3 | F77: 25 | G77: 50 | H77: =E77*G77 -> 150 | L77: 1 | M77: =IF(E77<=L77, "⚠️ REORDER", "✅ STABLE") -> ✅ STABLE
B78: PH-1078 | C78: Antitussives | D78: Dacold susp 100ml | E78: 2 | F78: 65 | G78: 150 | H78: =E78*G78 -> 300 | L78: 1 | M78: =IF(E78<=L78, "⚠️ REORDER", "✅ STABLE") -> ✅ STABLE
B79: PH-1079 | C79: Antitussives | D79: Dacof | E79: 0 | G79: 0 | H79: =E79*G79 -> 0 | L79: 1 | M79: =IF(E79<=L79, "⚠️ REORDER", "✅ STABLE") -> ⚠️ REORDER
B80: PH-1080 | C80: Antitussives | D80: Tricof | E80: 0 | G80: 0 | H80: =E80*G80 -> 0 | L80: 1 | M80: =IF(E80<=L80, "⚠️ REORDER", "✅ STABLE") -> ⚠️ REORDER
B81: PH-1081 | C81: Antitussives | D81: Ascoril expectorant 100ml | E81: 2 | F81: 260 | G81: 350 | H81: =E81*G81 -> 700 | L81: 1 | M81: =IF(E81<=L81, "⚠️ REORDER", "✅ STABLE") -> ✅ STABLE
B82: PH-1082 | C82: Antitussives | D82: Promethazine syrup | E82: 3 | F82: 25 | G82: 50 | H82: =E82*G82 -> 150 | L82: 1 | M82: =IF(E82<=L82, "⚠️ REORDER", "✅ STABLE") -> ✅ STABLE
B83: PH-1083 | C83: Antitussives | D83: Brozelin | E83: 0 | G83: 0 | H83: =E83*G83 -> 0 | L83: 1 | M83: =IF(E83<=L83, "⚠️ REORDER", "✅ STABLE") -> ⚠️ REORDER
B84: PH-1084 | C84: Antitussives | D84: Zefcoin | E84: 0 | G84: 0 | H84: =E84*G84 -> 0 | L84: 1 | M84: =IF(E84<=L84, "⚠️ REORDER", "✅ STABLE") -> ⚠️ REORDER
B85: PH-1085 | C85: Antacids | D85: relcer gel 100mls small | E85: 1 | F85: 285 | G85: 500 | H85: =E85*G85 -> 500 | L85: 1 | M85: =IF(E85<=L85, "⚠️ REORDER", "✅ STABLE") -> ⚠️ REORDER
B86: PH-1086 | C86: Antacids | D86: relcer gell 180ml | E86: 1 | F86: 380 | G86: 550 | H86: =E86*G86 -> 550 | L86: 1 | M86: =IF(E86<=L86, "⚠️ REORDER", "✅ STABLE") -> ⚠️ REORDER
B87: PH-1087 | C87: Antacids | D87: Buscopan hyoscine syrup 60 mls | E87: 3 | F87: 55 | G87: 150 | H87: =E87*G87 -> 450 | L87: 1 | M87: =IF(E87<=L87, "⚠️ REORDER", "✅ STABLE") -> ✅ STABLE
B88: PH-1088 | C88: Antacids | D88: Gastrogel gel 200ml | E88: 3 | F88: 225 | G88: 400 | H88: =E88*G88 -> 1200 | L88: 1 | M88: =IF(E88<=L88, "⚠️ REORDER", "✅ STABLE") -> ✅ STABLE
B89: PH-1089 | C89: Antacids | D89: Onecid | E89: 3 | F89: 35 | G89: 100 | H89: =E89*G89 -> 300 | L89: 1 | M89: =IF(E89<=L89, "⚠️ REORDER", "✅ STABLE") -> ✅ STABLE
B90: PH-1090 | C90: Antacids | D90: tryactin antacid | E90: 1 | F90: 35 | G90: 100 | H90: =E90*G90 -> 100 | L90: 1 | M90: =IF(E90<=L90, "⚠️ REORDER", "✅ STABLE") -> ⚠️ REORDER
B91: PH-1091 | C91: Antacids | D91: Nill acid | E91: 2 | F91: 145 | G91: 250 | H91: =E91*G91 -> 500 | L91: 1 | M91: =IF(E91<=L91, "⚠️ REORDER", "✅ STABLE") -> ✅ STABLE
B92: PH-1092 | C92: Antacids | D92: Sungel | E92: 0 | G92: 0 | H92: =E92*G92 -> 0 | L92: 1 | M92: =IF(E92<=L92, "⚠️ REORDER", "✅ STABLE") -> ⚠️ REORDER
B93: PH-1093 | C93: Antacids | D93: Ulgicid pinapples 200ml | E93: 1 | F93: 325 | G93: 500 | H93: =E93*G93 -> 500 | L93: 1 | M93: =IF(E93<=L93, "⚠️ REORDER", "✅ STABLE") -> ⚠️ REORDER
B94: PH-1094 | C94: Antacids | D94: Trugel | E94: 0 | G94: 0 | H94: =E94*G94 -> 0 | L94: 1 | M94: =IF(E94<=L94, "⚠️ REORDER", "✅ STABLE") -> ⚠️ REORDER
B95: PH-1095 | C95: Antacids | D95: Flatameal syrup 200ml | E95: 1 | F95: 295 | G95: 400 | H95: =E95*G95 -> 400 | L95: 1 | M95: =IF(E95<=L95, "⚠️ REORDER", "✅ STABLE") -> ⚠️ REORDER
B96: PH-1096 | C96: Antacids | D96: Catoximag | E96: 0 | G96: 0 | H96: =E96*G96 -> 0 | L96: 1 | M96: =IF(E96<=L96, "⚠️ REORDER", "✅ STABLE") -> ⚠️ REORDER
B97: PH-1097 | C97: Antacids | D97: Benagas | E97: 0 | G97: 0 | H97: =E97*G97 -> 0 | L97: 1 | M97: =IF(E97<=L97, "⚠️ REORDER", "✅ STABLE") -> ⚠️ REORDER
B98: PH-1098 | C98: Antacids | D98: Gaviscon | E98: 0 | G98: 0 | H98: =E98*G98 -> 0 | L98: 1 | M98: =IF(E98<=L98, "⚠️ REORDER", "✅ STABLE") -> ⚠️ REORDER
B99: PH-1099 | C99: Antacids | D99: Sculaphet gel | E99: 0 | G99: 0 | H99: =E99*G99 -> 0 | L99: 1 | M99: =IF(E99<=L99, "⚠️ REORDER", "✅ STABLE") -> ⚠️ REORDER
B100: PH-1100 | C100: Antacids | D100: Stopacid | E100: 0 | G100: 0 | H100: =E100*G100 -> 0 | L100: 1 | M100: =IF(E100<=L100, "⚠️ REORDER", "✅ STABLE") -> ⚠️ REORDER
B101: PH-1101 | C101: Appetite & Vitamins | D101: Cypon plus syrup | E101: 1 | F101: 298 | G101: 450 | H101: =E101*G101 -> 450 | L101: 1 | M101: =IF(E101<=L101, "⚠️ REORDER", "✅ STABLE") -> ⚠️ REORDER
B102: PH-1102 | C102: Appetite & Vitamins | D102: Seven seas cod liver oil syrup | E102: 1 | F102: 735 | G102: 1050 | H102: =E102*G102 -> 1050 | L102: 1 | M102: =IF(E102<=L102, "⚠️ REORDER", "✅ STABLE") -> ⚠️ REORDER
B103: PH-1103 | C103: Appetite & Vitamins | D103: Scotts | E103: 1 | F103: 535 | G103: 800 | H103: =E103*G103 -> 800 | L103: 1 | M103: =IF(E103<=L103, "⚠️ REORDER", "✅ STABLE") -> ⚠️ REORDER
B104: PH-1104 | C104: Appetite & Vitamins | D104: Gypon | E104: 0 | G104: 0 | H104: =E104*G104 -> 0 | L104: 1 | M104: =IF(E104<=L104, "⚠️ REORDER", "✅ STABLE") -> ⚠️ REORDER
B105: PH-1105 | C105: Appetite & Vitamins | D105: Cypomaltin | E105: 0 | G105: 0 | H105: =E105*G105 -> 0 | L105: 1 | M105: =IF(E105<=L105, "⚠️ REORDER", "✅ STABLE") -> ⚠️ REORDER
B106: PH-1106 | C106: Appetite & Vitamins | D106: ashtone | E106: 0 | G106: 0 | H106: =E106*G106 -> 0 | L106: 1 | M106: =IF(E106<=L106, "⚠️ REORDER", "✅ STABLE") -> ⚠️ REORDER
B107: PH-1107 | C107: Appetite & Vitamins | D107: Vastameal | E107: 0 | G107: 0 | H107: =E107*G107 -> 0 | L107: 1 | M107: =IF(E107<=L107, "⚠️ REORDER", "✅ STABLE") -> ⚠️ REORDER
B108: PH-1108 | C108: Appetite & Vitamins | D108: Uplift c | E108: 0 | G108: 0 | H108: =E108*G108 -> 0 | L108: 1 | M108: =IF(E108<=L108, "⚠️ REORDER", "✅ STABLE") -> ⚠️ REORDER
B109: PH-1109 | C109: Appetite & Vitamins | D109: cypro b plus syrup 200mls | E109: 1 | F109: 380 | G109: 450 | H109: =E109*G109 -> 450 | L109: 1 | M109: =IF(E109<=L109, "⚠️ REORDER", "✅ STABLE") -> ⚠️ REORDER
B110: PH-1110 | C110: Antihistamines | D110: axe brand (chapa shoka liquid) | E110: 1 | F110: 120 | G110: 200 | H110: =E110*G110 -> 200 | L110: 0 | M110: =IF(E110<=L110, "⚠️ REORDER", "✅ STABLE") -> ✅ STABLE
B111: PH-1111 | C111: Appetite & Vitamins | D111: Multivitamin syrup 100ml (euvitan) | E111: 9 | F111: 35 | G111: 100 | H111: =E111*G111 -> 900 | L111: 5 | M111: =IF(E111<=L111, "⚠️ REORDER", "✅ STABLE") -> ✅ STABLE
B112: PH-1112 | C112: Appetite & Vitamins | D112: Bonnisan | E112: 1 | F112: 350 | G112: 500 | H112: =E112*G112 -> 500 | L112: 1 | M112: =IF(E112<=L112, "⚠️ REORDER", "✅ STABLE") -> ⚠️ REORDER
B113: PH-1113 | C113: Appetite & Vitamins | D113: Infacol 55ml | E113: 1 | F113: 1230 | G113: 1700 | H113: =E113*G113 -> 1700 | L113: 1 | M113: =IF(E113<=L113, "⚠️ REORDER", "✅ STABLE") -> ⚠️ REORDER
B114: PH-1114 | C114: Appetite & Vitamins | D114: Coliza | E114: 0 | G114: 0 | H114: =E114*G114 -> 0 | L114: 1 | M114: =IF(E114<=L114, "⚠️ REORDER", "✅ STABLE") -> ⚠️ REORDER
B115: PH-1115 | C115: Appetite & Vitamins | D115: Lactulose lactulac solution 100ml | E115: 2 | F115: 320 | G115: 500 | H115: =E115*G115 -> 1000 | L115: 1 | M115: =IF(E115<=L115, "⚠️ REORDER", "✅ STABLE") -> ✅ STABLE
B116: PH-1116 | C116: mouth wash | D116: peardine Mouth wash | E116: 2 | F116: 85 | G116: 150 | H116: =E116*G116 -> 300 | L116: 1 | M116: =IF(E116<=L116, "⚠️ REORDER", "✅ STABLE") -> ✅ STABLE
B117: PH-1117 | C117: Blood Builders | D117: Ferrose | E117: 0 | G117: 0 | H117: =E117*G117 -> 0 | L117: 1 | M117: =IF(E117<=L117, "⚠️ REORDER", "✅ STABLE") -> ⚠️ REORDER
B118: PH-1118 | C118: Blood Builders | D118: Ranferon syrup 200ml | E118: 1 | F118: 380 | G118: 550 | H118: =E118*G118 -> 550 | L118: 1 | M118: =IF(E118<=L118, "⚠️ REORDER", "✅ STABLE") -> ⚠️ REORDER
B119: PH-1119 | C119: Ophthalmic & Otic | D119: Saline drops (nasal drops) | E119: 2 | F119: 22 | G119: 50 | H119: =E119*G119 -> 100 | L119: 1 | M119: =IF(E119<=L119, "⚠️ REORDER", "✅ STABLE") -> ✅ STABLE
B120: PH-1120 | C120: Ophthalmic & Otic | D120: Efedrin ear drops | E120: 0 | G120: 0 | H120: =E120*G120 -> 0 | L120: 1 | M120: =IF(E120<=L120, "⚠️ REORDER", "✅ STABLE") -> ⚠️ REORDER
B121: PH-1121 | C121: Fluids | D121: normal saline 500ml (NS) | E121: 3 | F121: 70 | G121: 150 | H121: =E121*G121 -> 450 | L121: 1 | M121: =IF(E121<=L121, "⚠️ REORDER", "✅ STABLE") -> ✅ STABLE
B122: PH-1122 | C122: Ophthalmic & Otic | D122: Gentamycin eye drops | E122: 10 | F122: 15 | G122: 100 | H122: =E122*G122 -> 1000 | L122: 5 | M122: =IF(E122<=L122, "⚠️ REORDER", "✅ STABLE") -> ✅ STABLE
B123: PH-1123 | C123: Ophthalmic & Otic | D123: Ciprofloxacin ear drops | E123: 2 | F123: 110 | G123: 200 | H123: =E123*G123 -> 400 | L123: 1 | M123: =IF(E123<=L123, "⚠️ REORDER", "✅ STABLE") -> ✅ STABLE
B124: PH-1124 | C124: Ophthalmic & Otic | D124: Probeta N eye drops | E124: 2 | F124: 125 | G124: 200 | H124: =E124*G124 -> 400 | L124: 1 | M124: =IF(E124<=L124, "⚠️ REORDER", "✅ STABLE") -> ✅ STABLE
B125: PH-1125 | C125: Antibiotics | D125: Nystatin oral drops | E125: 2 | F125: 65 | G125: 150 | H125: =E125*G125 -> 300 | L125: 1 | M125: =IF(E125<=L125, "⚠️ REORDER", "✅ STABLE") -> ✅ STABLE
B126: PH-1126 | C126: Ophthalmic & Otic | D126: genta glax | E126: 0 | G126: 0 | H126: =E126*G126 -> 0 | L126: 1 | M126: =IF(E126<=L126, "⚠️ REORDER", "✅ STABLE") -> ⚠️ REORDER
B127: PH-1127 | C127: Ophthalmic & Otic | D127: dexneo (dexomet N eye drops) | E127: 1 | F127: 70 | G127: 150 | H127: =E127*G127 -> 150 | L127: 1 | M127: =IF(E127<=L127, "⚠️ REORDER", "✅ STABLE") -> ⚠️ REORDER
B128: PH-1128 | C128: Ophthalmic & Otic | D128: maxol | E128: 0 | G128: 0 | H128: =E128*G128 -> 0 | L128: 1 | M128: =IF(E128<=L128, "⚠️ REORDER", "✅ STABLE") -> ⚠️ REORDER
B129: PH-1129 | C129: Ophthalmic & Otic | D129: occulast | E129: 0 | G129: 0 | H129: =E129*G129 -> 0 | L129: 1 | M129: =IF(E129<=L129, "⚠️ REORDER", "✅ STABLE") -> ⚠️ REORDER
...

Sheet Sales
B2: Pharmacy Sales Ledger Tracking
B4: Invoice No | C4: Date | D4: Item ID | E4: Item Name | F4: Qty Sold | G4: Unit Price (KES) | H4: Gross Amount (KES) | I4: Unit COG | J4: Gross COG (KES) | K4: Net Profit (KES)
B5: =IF(ISBLANK(B2), "", COUNTA($B$2:B2)) -> 1 | C5: 27/06/2026 | E5: Cprofloxacin eye drops | F5: 1 | G5: 150 | H5: =F5*G5 -> 150 | I5: 110 | J5: =F5*I5 -> 110 | K5: =H5-J5 -> 40
B6: 2 | E6: omeprazole | F6: 2 | G6: 5 | H6: =F6*G6 -> 10 | I6: 0.9 | J6: =F6*I6 -> 1.8 | K6: =H6-J6 -> 8.2
B7: 3 | E7: Azythromycin | F7: 1 | G7: 100 | H7: =F7*G7 -> 100 | I7: 50 | J7: =F7*I7 -> 50 | K7: =H7-J7 -> 50
B8: 4 | E8: brufen tabs | F8: 10 | G8: 3 | H8: =F8*G8 -> 30 | I8: 1.3 | J8: =F8*I8 -> 13 | K8: =H8-J8 -> 17
B9: 5 | C9: 28/06/2026 | E9: mara moja | F9: 1 | G9: 10 | H9: =F9*G9 -> 10 | I9: 7 | J9: =F9*I9 -> 7 | K9: =H9-J9 -> 3
B10: 6 | E10: lobak | F10: 10 | G10: 20 | H10: =F10*G10 -> 200 | I10: 10 | J10: =F10*I10 -> 100 | K10: =H10-J10 -> 100
B11: 7 | E11: trust classic | F11: 1 | G11: 50 | H11: =F11*G11 -> 50 | I11: 26 | J11: =F11*I11 -> 26 | K11: =H11-J11 -> 24
E12: apc | F12: 10 | G12: 2 | H12: =F12*G12 -> 20 | I12: 1.2 | J12: =F12*I12 -> 12 | K12: =H12-J12 -> 8
C13: 29/06/2026 | E13: doxycycline | F13: 10 | G13: 10 | H13: =F13*G13 -> 100 | I13: 2.1 | J13: =F13*I13 -> 21 | K13: =H13-J13 -> 79
E14: amoxyl | F14: 15 | G14: 6.7 | H14: =F14*G14 -> 100.5 | I14: 3 | J14: =F14*I14 -> 45 | K14: =H14-J14 -> 55.5
E15: pcm | F15: 10 | G15: 2 | H15: =F15*G15 -> 20 | I15: 0.9 | J15: =F15*I15 -> 9 | K15: =H15-J15 -> 11
E16: hydrocortisone cream | F16: 1 | G16: 100 | H16: =F16*G16 -> 100 | I16: 28 | J16: =F16*I16 -> 28 | K16: =H16-J16 -> 72
E17: amoxyl | F17: 15 | G17: 6.6 | H17: =F17*G17 -> 99 | I17: 3 | J17: =F17*I17 -> 45 | K17: =H17-J17 -> 54
E18: piroxicam | F18: 10 | G18: 5 | H18: =F18*G18 -> 50 | I18: 0.85 | J18: =F18*I18 -> 8.5 | K18: =H18-J18 -> 41.5
C19: 30/06/2026 | E19: omeprazole | F19: 2 | G19: 5 | H19: =F19*G19 -> 10 | I19: 0.9 | J19: =F19*I19 -> 1.8 | K19: =H19-J19 -> 8.2
E20: montelucast | F20: 1 | G20: 25 | H20: =F20*G20 -> 25 | I20: 10.5 | J20: =F20*I20 -> 10.5 | K20: =H20-J20 -> 14.5
E21: maramoja | F21: 2 | G21: 10 | H21: =F21*G21 -> 20 | I21: 7 | J21: =F21*I21 -> 14 | K21: =H21-J21 -> 6
E22: cold caps | F22: 2 | G22: 20 | H22: =F22*G22 -> 40 | I22: 8 | J22: =F22*I22 -> 16 | K22: =H22-J22 -> 24
E23: cetrizine | F23: 2 | G23: 5 | H23: =F23*G23 -> 10 | I23: 0.9 | J23: =F23*I23 -> 1.8 | K23: =H23-J23 -> 8.2
E24: floxapen | F24: 20 | G24: 12.5 | H24: =F24*G24 -> 250 | I24: 6.7 | J24: =F24*I24 -> 134 | K24: =H24-J24 -> 116
E25: omeprazole | F25: 4 | G25: 5 | H25: =F25*G25 -> 20 | I25: 0.9 | J25: =F25*I25 -> 3.6 | K25: =H25-J25 -> 16.4
E26: apc | F26: 5 | G26: 2 | H26: =F26*G26 -> 10 | I26: 1.2 | J26: =F26*I26 -> 6 | K26: =H26-J26 -> 4
E27: cetrizine | F27: 2 | G27: 5 | H27: =F27*G27 -> 10 | I27: 0.9 | J27: =F27*I27 -> 1.8 | K27: =H27-J27 -> 8.2
E28: maramoja | F28: 1 | G28: 10 | H28: =F28*G28 -> 10 | I28: 7 | J28: =F28*I28 -> 7 | K28: =H28-J28 -> 3
C29: 46029 | E29: omeprazole | F29: 8 | G29: 5 | H29: =F29*G29 -> 40 | I29: 0.9 | J29: =F29*I29 -> 7.2 | K29: =H29-J29 -> 32.8
E30: omeprazole | F30: 2 | G30: 5 | H30: =F30*G30 -> 10 | I30: 0.9 | J30: =F30*I30 -> 1.8 | K30: =H30-J30 -> 8.2
C31: 46060 | E31: omeprazole | F31: 2 | G31: 5 | H31: =F31*G31 -> 10 | I31: 0.9 | J31: =F31*I31 -> 1.8 | K31: =H31-J31 -> 8.2
E32: montelucast | F32: 1 | G32: 25 | H32: =F32*G32 -> 25 | I32: 10.5 | J32: =F32*I32 -> 10.5 | K32: =H32-J32 -> 14.5
E33: maramoja | F33: 1 | G33: 10 | H33: =F33*G33 -> 10 | I33: 7 | J33: =F33*I33 -> 7 | K33: =H33-J33 -> 3
E34: eno | F34: 1 | G34: 20 | H34: =F34*G34 -> 20 | I34: 17 | J34: =F34*I34 -> 17 | K34: =H34-J34 -> 3
E35: omeprazole | F35: 2 | G35: 5 | H35: =F35*G35 -> 10 | I35: 0.9 | J35: =F35*I35 -> 1.8 | K35: =H35-J35 -> 8.2
E36: kaluma lozzonges | F36: 1 | G36: 20 | H36: =F36*G36 -> 20 | I36: 12 | J36: =F36*I36 -> 12 | K36: =H36-J36 -> 8
E37: kaluma tablets | F37: 1 | G37: 10 | H37: =F37*G37 -> 10 | I37: 6 | J37: =F37*I37 -> 6 | K37: =H37-J37 -> 4
E38: amoxyl | F38: 5 | G38: 10 | H38: =F38*G38 -> 50 | I38: 3 | J38: =F38*I38 -> 15 | K38: =H38-J38 -> 35
E39: prednisolone | F39: 10 | G39: 2 | H39: =F39*G39 -> 20 | I39: 0.65 | J39: =F39*I39 -> 6.5 | K39: =H39-J39 -> 13.5
C40: 46088 | E40: promethazine | F40: 4 | G40: 5 | H40: =F40*G40 -> 20 | I40: 1.9 | J40: =F40*I40 -> 7.6 | K40: =H40-J40 -> 12.4
E41: celestamine | F41: 1 | G41: 20 | H41: =F41*G41 -> 20 | I41: 8.8 | J41: =F41*I41 -> 8.8 | K41: =H41-J41 -> 11.2
E42: pcm | F42: 10 | G42: 2 | H42: =F42*G42 -> 20 | I42: 0.9 | J42: =F42*I42 -> 9 | K42: =H42-J42 -> 11
E43: pcm | F43: 10 | G43: 2 | H43: =F43*G43 -> 20 | I43: 0.9 | J43: =F43*I43 -> 9 | K43: =H43-J43 -> 11
E44: pcm | F44: 10 | G44: 2 | H44: =F44*G44 -> 20 | I44: 0.9 | J44: =F44*I44 -> 9 | K44: =H44-J44 -> 11
E45: Azythromycin | F45: 1 | G45: 100 | H45: =F45*G45 -> 100 | I45: 50 | J45: =F45*I45 -> 50 | K45: =H45-J45 -> 50
E46: strepsils | F46: 2 | G46: 25 | H46: =F46*G46 -> 50 | I46: 17 | J46: =F46*I46 -> 34 | K46: =H46-J46 -> 16
E47: celestamine | F47: 1 | G47: 20 | H47: =F47*G47 -> 20 | I47: 8.8 | J47: =F47*I47 -> 8.8 | K47: =H47-J47 -> 11.2
E48: abz | F48: 1 | G48: 50 | H48: =F48*G48 -> 50 | I48: 10 | J48: =F48*I48 -> 10 | K48: =H48-J48 -> 40
E49: Azythromycin | F49: 1 | G49: 100 | H49: =F49*G49 -> 100 | I49: 50 | J49: =F49*I49 -> 50 | K49: =H49-J49 -> 50
E50: brufen tabs | F50: 10 | G50: 2 | H50: =F50*G50 -> 20 | I50: 1.3 | J50: =F50*I50 -> 13 | K50: =H50-J50 -> 7
E51: amoxiclav | F51: 1 | G51: 300 | H51: =F51*G51 -> 300 | I51: 110 | J51: =F51*I51 -> 110 | K51: =H51-J51 -> 190
E52: flugone | F52: 2 | G52: 20 | H52: =F52*G52 -> 40 | I52: 13 | J52: =F52*I52 -> 26 | K52: =H52-J52 -> 14
... E63: fever pyn | F63: 1 | G63: 140 | H63: =F63*G63 -> 140 | I63: 55 | J63: =F63*I63 -> 55 | K63: =H63-J63 -> 85
C64: 46119 | E64: pcm | F64: 10 | G64: 2 | H64: =F64*G64 -> 20 | I64: 0.9 | J64: =F64*I64 -> 9 | K64: =H64-J64 -> 11
E65: omeprazole | F65: 6 | G65: 5 | H65: =F65*G65 -> 30 | I65: 0.9 | J65: =F65*I65 -> 5.4 | K65: =H65-J65 -> 24.6
E66: pcm | F66: 10 | G66: 2 | H66: =F66*G66 -> 20 | I66: 0.9 | J66: =F66*I66 -> 9 | K66: =H66-J66 -> 11
E67: montelucast | F67: 1 | G67: 25 | H67: =F67*G67 -> 25 | I67: 10.5 | J67: =F67*I67 -> 10.5 | K67: =H67-J67 -> 14.5
E68: abz | F68: 1 | G68: 50 | H68: =F68*G68 -> 50 | I68: 10 | J68: =F68*I68 -> 10 | K68: =H68-J68 -> 40
E69: pcm | F69: 10 | G69: 2 | H69: =F69*G69 -> 20 | I69: 0.9 | J69: =F69*I69 -> 9 | K69: =H69-J69 -> 11
C70: 46149 | E70: abz | F70: 1 | G70: 50 | H70: =F70*G70 -> 50 | I70: 10 | J70: =F70*I70 -> 10 | K70: =H70-J70 -> 40
E71: omeprazole | F71: 1 | G71: 5 | H71: =F71*G71 -> 5 | I71: 0.9 | J71: =F71*I71 -> 0.9 | K71: =H71-J71 -> 4.1
E72: pcm | F72: 10 | G72: 2 | H72: =F72*G72 -> 20 | I72: 0.9 | J72: =F72*I72 -> 9 | K72: =H72-J72 -> 11
E73: brufen tabs | F73: 10 | G73: 2 | H73: =F73*G73 -> 20 | I73: 1.3 | J73: =F73*I73 -> 13 | K73: =H73-J73 -> 7
E74: Azythromycin | F74: 1 | G74: 100 | H74: =F74*G74 -> 100 | I74: 50 | J74: =F74*I74 -> 50 | K74: =H74-J74 -> 50
E75: cetrihist cough syrup | F75: 1 | G75: 100 | H75: =F75*G75 -> 100 | I75: 46 | J75: =F75*I75 -> 46 | K75: =H75-J75 -> 54
E76: omeprazole | F76: 1 | G76: 5 | H76: =F76*G76 -> 5 | I76: 0.9 | J76: =F76*I76 -> 0.9 | K76: =H76-J76 -> 4.1
E77: esomeprazole 20mg | F77: 1 | G77: 10 | H77: =F77*G77 -> 10 | I77: 2.3 | J77: =F77*I77 -> 2.3 | K77: =H77-J77 -> 7.7
E78: zulu | F78: 1 | G78: 50 | H78: =F78*G78 -> 50 | I78: 39 | J78: =F78*I78 -> 39 | K78: =H78-J78 -> 11
E79: pdt test kit | F79: 1 | G79: 50 | H79: =F79*G79 -> 50 | I79: 10 | J79: =F79*I79 -> 10 | K79: =H79-J79 -> 40
E80: maramoja | F80: 1 | G80: 10 | H80: =F80*G80 -> 10 | I80: 7 | J80: =F80*I80 -> 7 | K80: =H80-J80 -> 3
E81: brufen tabs | F81: 10 | G81: 2 | H81: =F81*G81 -> 20 | I81: 1.3 | J81: =F81*I81 -> 13 | K81: =H81-J81 -> 7
C82: 46180 | E82: omeprazole | F82: 3 | G82: 5 | H82: =F82*G82 -> 15 | I82: 0.9 | J82: =F82*I82 -> 2.7 | K82: =H82-J82 -> 12.3
E83: cypro B tabs | F83: 2 | G83: 20 | H83: =F83*G83 -> 40 | I83: 12.6 | J83: =F83*I83 -> 25.2 | K83: =H83-J83 -> 14.8
E84: epiderm cream | F84: 1 | G84: 110 | H84: =F84*G84 -> 110 | I84: 50 | J84: =F84*I84 -> 50 | K84: =H84-J84 -> 60
E85: dolact mr | F85: 2 | G85: 25 | H85: =F85*G85 -> 50 | I85: 20 | J85: =F85*I85 -> 40 | K85: =H85-J85 -> 10
E86: kaluma tablets | F86: 1 | G86: 10 | H86: =F86*G86 -> 10 | I86: 6 | J86: =F86*I86 -> 6 | K86: =H86-J86 -> 4
E87: p2 original | F87: 1 | G87: 200 | H87: =F87*G87 -> 200 | I87: 165 | J87: =F87*I87 -> 165 | K87: =H87-J87 -> 35
C88: 46210 | E88: Natoa | F88: 1 | G88: 100 | H88: =F88*G88 -> 100 | I88: 45 | J88: =F88*I88 -> 45 | K88: =H88-J88 -> 55
E89: bandage 4 inch | F89: 1 | G89: 50 | H89: =F89*G89 -> 50 | I89: 25 | J89: =F89*I89 -> 25 | K89: =H89-J89 -> 25
E90: pdt test kit | F90: 1 | G90: 50 | H90: =F90*G90 -> 50 | I90: 10 | J90: =F90*I90 -> 10 | K90: =H90-J90 -> 40
E91: diclofenac tablets | F91: 2 | G91: 5 | H91: =F91*G91 -> 10 | I91: 0.65 | J91: =F91*I91 -> 1.3 | K91: =H91-J91 -> 8.7
E92: apc | F92: 5 | G92: 2 | H92: =F92*G92 -> 10 | I92: 1.2 | J92: =F92*I92 -> 6 | K92: =H92-J92 -> 4
E93: trust classic | F93: 1 | G93: 50 | H93: =F93*G93 -> 50 | I93: 25 | J93: =F93*I93 -> 25 | K93: =H93-J93 -> 25
C94: 46241 | E94: hiv test kit | F94: 1 | G94: 150 | H94: =F94*G94 -> 150 | I94: 55 | J94: =F94*I94 -> 55 | K94: =H94-J94 -> 95
E95: surgical spirit 500mls | F95: 1 | G95: 100 | H95: =F95*G95 -> 100 | I95: 85 | J95: =F95*I95 -> 85 | K95: =H95-J95 -> 15
E96: cotton wool 100g | F96: 1 | G96: 100 | H96: =F96*G96 -> 100 | I96: 88 | J96: =F96*I96 -> 88 | K96: =H96-J96 -> 12
E97: omeprazole | F97: 4 | G97: 5 | H97: =F97*G97 -> 20 | I97: 0.9 | J97: =F97*I97 -> 3.6 | K97: =H97-J97 -> 16.4
E98: cetrizine | F98: 10 | G98: 5 | H98: =F98*G98 -> 50 | I98: 0.9 | J98: =F98*I98 -> 9 | K98: =H98-J98 -> 41
E99: amoxyl | F99: 5 | G99: 10 | H99: =F99*G99 -> 50 | I99: 3 | J99: =F99*I99 -> 15 | K99: =H99-J99 -> 35
E100: Azythromycin | F100: 1 | G100: 150 | H100: =F100*G100 -> 150 | I100: 50 | J100: =F100*I100 -> 50 | K100: =H100-J100 -> 100
E101: cetrihist cough syrup | F101: 1 | G101: 100 | H101: =F101*G101 -> 100 | I101: 46 | J101: =F101*I101 -> 46 | K101: =H101-J101 -> 54
E102: septrin 960 | F102: 10 | G102: 10 | H102: =F102*G102 -> 100 | I102: 3.2 | J102: =F102*I102 -> 32 | K102: =H102-J102 -> 68
E103: p2 Generic | F103: 1 | G103: 100 | H103: =F103*G103 -> 100 | I103: 22 | J103: =F103*I103 -> 22 | K103: =H103-J103 -> 78
E104: abz | F104: 1 | G104: 50 | H104: =F104*G104 -> 50 | I104: 15 | J104: =F104*I104 -> 15 | K104: =H104-J104 -> 35
E105: lobak | F105: 1 | G105: 20 | H105: =F105*G105 -> 20 | I105: 10 | J105: =F105*I105 -> 10 | K105: =H105-J105 -> 10
C106: 46272 | E106: cetrizine | F106: 4 | G106: 5 | H106: =F106*G106 -> 20 | I106: 0.9 | J106: =F106*I106 -> 3.6 | K106: =H106-J106 -> 16.4
E107: pcm | F107: 10 | G107: 2 | H107: =F107*G107 -> 20 | I107: 0.9 | J107: =F107*I107 -> 9 | K107: =H107-J107 -> 11
E108: p2 original | F108: 1 | G108: 180 | H108: =F108*G108 -> 180 | I108: 165 | J108: =F108*I108 -> 165 | K108: =H108-J108 -> 15
E109: femiplan pills | F109: 1 | G109: 120 | H109: =F109*G109 -> 120 | I109: 100 | J109: =F109*I109 -> 100 | K109: =H109-J109 -> 20
E110: strepsils | F110: 1 | G110: 20 | H110: =F110*G110 -> 20 | I110: 17 | J110: =F110*I110 -> 17 | K110: =H110-J110 -> 3
E111: cetrizine | F111: 4 | G111: 5 | H111: =F111*G111 -> 20 | I111: 0.9 | J111: =F111*I111 -> 3.6 | K111: =H111-J111 -> 16.4
E112: pcm | F112: 10 | G112: 2 | H112: =F112*G112 -> 20 | I112: 0.9 | J112: =F112*I112 -> 9 | K112: =H112-J112 -> 11
...

Sheet Transactions
B2: Pharmacy Transactions Ledger Tracking
B4: Expenditure ID | C4: Date | D4: Money IN/profits | E4: Item Name | F4: Money OUT/Expenditure | G4: Quantity | H4: User Account | I4: Verified By
B5: JULY total monthly earnings | C5: 31/07/2026 | D5: 22397
B6: july rent | C6: 20/07/2026 | F6: 8000
B7: July electricity bill | F7: 600
B8: July wifi bill
B9: july salary payments | F9: 6000
B10: Restocking amount | D10: 11150 | F10: 10109
B11: July net profit | C11: 31/07/2026 | D11: 11248
B13: August total restocking cost
B14: August shop rent
B15: August electricity bill
B16: August salary payments
B17: August

Sheet Purchase Orders
B2: Pharmacy Purchase Orders Ledger Tracking
B4: Item | C4: Date purchase | D4: Supplier Amount | E4: Item Required | F4: Order Qty | G4: Estimated Unit Cost | H4: Delivery Window Status
B5: RSTOCKING OUT OF STOCK ITEMS | D5: 2450
B6: RESTOCKING OUT OF STOCK ITEMS | C6: 20/07/2026 | D6: 2092
B7: RESTOCKING OUT OF STOCK ITEMS | C7: 14/07/2026 | D7: 1052
B8: RESTOCKING OUT OF STOCK ITEMS | C8: 30/07/2026 | D8: 630
B9: RESTOCKING OUT OF STOCK ITEMS | C9: 29/07/2025 | D9: 190
B10: RESTOCKING OUT OF STOCK ITEMS | C10: 13/07/2025 | D10: 600
B11: RESTOCKING OUT OF STOCK ITEMS | C11: 28/07/2025 | D11: 1930
B12: TOTAL july restocking Expenditure | D12: =SUM(D4:D11) -> 8944
B13: AUGUST EXPENDITURE
B14: HOUSE RENT | C14: 46181 | D14: 6000
B15: Restocking of drugs that were OS | C15: 46181 | D15: 1165
B16: House Shopping | C16: 46089 | D16: 3000
B17: Restocking of drugs that were OS | C17: 15/08/2026 | D17: 2300
B18: printing and setting direction poster | C18: 20/08/2026 | D18: 1000
B19: Restocking of drugs that were OS | C19: 20/08/2026 | D19: 960
B20: refilling water | C20: 21/08/2026 | D20: 250

Sheet Suppliers
B2: Pharmacy Suppliers Ledger Tracking
B4: Supplier ID | C4: Company Name | D4: Contact Person | E4: Phone Number | F4: Email Address | G4: Tax ID / PIN | H4: Outstanding Balance (KES)

Sheet DDA Register
B2: Pharmacy DDA Register Ledger Tracking
B4: DDA Log Ref | C4: Date | D4: Item ID (Controlled) | E4: Patient Name | F4: Prescribing Doctor | G4: Qty Dispensed | H4: Doctor License No | I4: Pharmacist Signature

Sheet Expiry Register
B2: Pharmacy Expiry Register Ledger Tracking
B4: Log ID | C4: Item ID | D4: Item Name | E4: Batch Number | F4: Expiry Date | G4: Days Remaining | H4: Risk Severity Status
G5: =F5-TODAY() -> -46270 | H5: =IF(G5<=0,"❌ EXPIRED",IF(G5<=90,"⚠️ CRITICAL","✅ SAFE")) -> ❌ EXPIRED

Sheet Stock Take
B2: Pharmacy Stock Take Ledger Tracking
B4: Audit Date | C4: Item ID | D4: Item Name | E4: System Qty | F4: Physical Counted Qty | G4: Variance Qty | H4: Financial Discrepancy | I4: Action Taken
G5: =F5-E5 -> 0 | H5: =G5*'Master Inventory'!F5 -> 0
